odoo10_addon_website_legal_page-10.0.1.2.0-py2.7-nspkg.pth
odoo/addons/website_legal_page/README.rst
odoo/addons/website_legal_page/__init__.py
odoo/addons/website_legal_page/__manifest__.py
odoo/addons/website_legal_page/controllers/__init__.py
odoo/addons/website_legal_page/controllers/main.py
odoo/addons/website_legal_page/i18n/bg.po
odoo/addons/website_legal_page/i18n/ca.po
odoo/addons/website_legal_page/i18n/de.po
odoo/addons/website_legal_page/i18n/el_GR.po
odoo/addons/website_legal_page/i18n/es.po
odoo/addons/website_legal_page/i18n/fr.po
odoo/addons/website_legal_page/i18n/hr_HR.po
odoo/addons/website_legal_page/i18n/it.po
odoo/addons/website_legal_page/i18n/nb_NO.po
odoo/addons/website_legal_page/i18n/pt_BR.po
odoo/addons/website_legal_page/i18n/pt_PT.po
odoo/addons/website_legal_page/i18n/ru.po
odoo/addons/website_legal_page/i18n/sl.po
odoo/addons/website_legal_page/migrations/10.0.1.0.0/pre-migrate.py
odoo/addons/website_legal_page/static/description/icon.png
odoo/addons/website_legal_page/static/description/johnny-automatic-scales-of-justice.svg
odoo/addons/website_legal_page/tests/__init__.py
odoo/addons/website_legal_page/tests/test_controller.py
odoo/addons/website_legal_page/views/reusable_templates.xml
odoo/addons/website_legal_page/views/website_legal.xml
odoo/addons/website_legal_page/views/website_privacy.xml
odoo/addons/website_legal_page/views/website_terms.xml
odoo10_addon_website_legal_page-10.0.1.2.0.dist-info/DESCRIPTION.rst
odoo10_addon_website_legal_page-10.0.1.2.0.dist-info/METADATA
odoo10_addon_website_legal_page-10.0.1.2.0.dist-info/RECORD
odoo10_addon_website_legal_page-10.0.1.2.0.dist-info/WHEEL
odoo10_addon_website_legal_page-10.0.1.2.0.dist-info/metadata.json
odoo10_addon_website_legal_page-10.0.1.2.0.dist-info/namespace_packages.txt
odoo10_addon_website_legal_page-10.0.1.2.0.dist-info/top_level.txt
