Metadata-Version: 2.0
Name: odoo10-addon-website-legal-page
Version: 10.0.1.2.0
Summary: Website Legal Page
Home-page: https://www.tecnativa.com
Author: Antiun Ingeniería S.L., Tecnativa, LasLabs, Odoo Community Association (OCA)
Author-email: support@odoo-community.org
License: AGPL-3
Platform: UNKNOWN
Classifier: Programming Language :: Python
Classifier: Framework :: Odoo
Classifier: License :: OSI Approved :: GNU Affero General Public License v3
Requires-Python: ~=2.7
Requires-Dist: odoo (<10.1dev,>=10.0)
